dagster_rudderstack/__init__.py
dagster_rudderstack/types.py
dagster_rudderstack/ops/__init__.py
dagster_rudderstack/ops/profiles.py
dagster_rudderstack/ops/retl.py
dagster_rudderstack/resources/__init__.py
dagster_rudderstack/resources/rudderstack.py
dagster_rudderstack-1.3.0.dist-info/licenses/LICENSE
dagster_rudderstack-1.3.0.dist-info/METADATA
dagster_rudderstack-1.3.0.dist-info/WHEEL
dagster_rudderstack-1.3.0.dist-info/top_level.txt
dagster_rudderstack-1.3.0.dist-info/RECORD
