Metadata-Version: 2.4
Name: dagster_rudderstack
Version: 1.3.0
Summary: A Dagster library for triggering Reverse ETL syncs in RudderStack.
License:                                  Apache License
Requires-Python: >=3.11
License-File: LICENSE
Requires-Dist: dagster>=1.6.14
Requires-Dist: pydantic>=2.8.2
Requires-Dist: pytest>=7.3.1
Requires-Dist: requests>=2.32.3
Requires-Dist: responses>=0.25.0
Requires-Dist: setuptools>=80.0.0
Requires-Dist: zipp>=3.19.1
Dynamic: license-file
